ugropy/__init__.py
ugropy/constants.py
ugropy/groups.py
ugropy/core/__init__.py
ugropy/core/checks.py
ugropy/core/get_rdkit_object.py
ugropy/core/frag_classes/__init__.py
ugropy/core/frag_classes/abdulelah_gani/__init__.py
ugropy/core/frag_classes/abdulelah_gani/abdulelah_gani.py
ugropy/core/frag_classes/abdulelah_gani/abdulelah_gani_pst.py
ugropy/core/frag_classes/abdulelah_gani/abdulelah_gani_pst_result.py
ugropy/core/frag_classes/abdulelah_gani/abdulelah_gani_result.py
ugropy/core/frag_classes/base/__init__.py
ugropy/core/frag_classes/base/fragmentation_model.py
ugropy/core/frag_classes/base/fragmentation_result.py
ugropy/core/frag_classes/gibbs_model/__init__.py
ugropy/core/frag_classes/gibbs_model/gibbs_model.py
ugropy/core/frag_classes/gibbs_model/gibbs_result.py
ugropy/core/frag_classes/joback/__init__.py
ugropy/core/frag_classes/joback/joback_model.py
ugropy/core/frag_classes/joback/joback_result.py
ugropy/core/ilp_solvers/__init__.py
ugropy/core/ilp_solvers/default_solver.py
ugropy/core/ilp_solvers/ilp_solver.py
ugropy/groupscsv/abdulelah_gani/properties_biases.csv
ugropy/groupscsv/abdulelah_gani/properties_contributions.csv
ugropy/groupscsv/abdulelah_gani/primary/info.csv
ugropy/groupscsv/abdulelah_gani/primary/primary.csv
ugropy/groupscsv/abdulelah_gani/secondary/info.csv
ugropy/groupscsv/abdulelah_gani/secondary/secondary.csv
ugropy/groupscsv/abdulelah_gani/tertiary/info.csv
ugropy/groupscsv/abdulelah_gani/tertiary/tertiary.csv
ugropy/groupscsv/constantinou_gani/primary/c_g_prymary_subgroups.csv
ugropy/groupscsv/constantinou_gani/primary/cg_problematics.csv
ugropy/groupscsv/constantinou_gani/primary/hideouts.csv
ugropy/groupscsv/constantinou_gani/primary/properties_prymary_contrib.csv
ugropy/groupscsv/constantinou_gani/secondary/structures.csv
ugropy/groupscsv/dortmund/dortmund_info.csv
ugropy/groupscsv/dortmund/dortmund_maingroups.csv
ugropy/groupscsv/dortmund/dortmund_subgroups.csv
ugropy/groupscsv/joback/joback_subgroups.csv
ugropy-3.1.6.dist-info/licenses/LICENSE
ugropy-3.1.6.dist-info/METADATA
ugropy-3.1.6.dist-info/WHEEL
ugropy-3.1.6.dist-info/top_level.txt
ugropy-3.1.6.dist-info/RECORD
