Metadata-Version: 2.4
Name: ugropy
Version: 3.1.6
Summary: Get UNIFAC functional groups of PubChem compounds or SMILES representation.
Author-email: "Brandolín, Salvador Eduardo" <salvadorebrandolin@mi.unc.edu.ar>
License: The MIT License
Project-URL: Homepage, https://github.com/ipqa-research/ugropy
Keywords: UNIFAC,functional group,thermodynamics,chemical engineering
Classifier: Development Status :: 1 - Planning
Classifier: Intended Audience :: Science/Research
Classifier: License :: OSI Approved :: MIT License
Classifier: Operating System :: OS Independent
Classifier: Programming Language :: Python :: 3.10
Classifier: Topic :: Scientific/Engineering
License-File: LICENSE
Requires-Dist: rdkit>=2023.9.5
Requires-Dist: pandas>=2.0.3
Requires-Dist: pubchempy>=1.0.4
Requires-Dist: pint>=0.22
Requires-Dist: pulp>=2.9.0; sys_platform != "darwin"
Requires-Dist: pulp==2.9.0; sys_platform == "darwin"
Dynamic: license-file
